MANIFEST.in
setup.cfg
setup.py
beyondskins/__init__.py
beyondskins.ploneday.site2009.egg-info/PKG-INFO
beyondskins.ploneday.site2009.egg-info/SOURCES.txt
beyondskins.ploneday.site2009.egg-info/dependency_links.txt
beyondskins.ploneday.site2009.egg-info/entry_points.txt
beyondskins.ploneday.site2009.egg-info/namespace_packages.txt
beyondskins.ploneday.site2009.egg-info/not-zip-safe
beyondskins.ploneday.site2009.egg-info/requires.txt
beyondskins.ploneday.site2009.egg-info/top_level.txt
beyondskins/ploneday/__init__.py
beyondskins/ploneday/site2009/README.txt
beyondskins/ploneday/site2009/__init__.py
beyondskins/ploneday/site2009/configure.zcml
beyondskins/ploneday/site2009/profiles.zcml
beyondskins/ploneday/site2009/setuphandlers.py
beyondskins/ploneday/site2009/skins.zcml
beyondskins/ploneday/site2009/tests.py
beyondskins/ploneday/site2009/version.txt
beyondskins/ploneday/site2009/browser/__init__.py
beyondskins/ploneday/site2009/browser/configure.zcml
beyondskins/ploneday/site2009/browser/interfaces.py
beyondskins/ploneday/site2009/browser/viewlets.py
beyondskins/ploneday/site2009/browser/images/README.txt
beyondskins/ploneday/site2009/browser/stylesheets/README.txt
beyondskins/ploneday/site2009/browser/templates/colophon.pt
beyondskins/ploneday/site2009/browser/templates/footer.pt
beyondskins/ploneday/site2009/browser/templates/viewlet.pt
beyondskins/ploneday/site2009/doc/__init__.py
beyondskins/ploneday/site2009/doc/browser.txt
beyondskins/ploneday/site2009/doc/sky-wdp2009.jpg
beyondskins/ploneday/site2009/locales/beyondskins.ploneday.site2009.pot
beyondskins/ploneday/site2009/locales/manual.pot
beyondskins/ploneday/site2009/locales/rebuildAll.sh
beyondskins/ploneday/site2009/locales/pt_BR/LC_MESSAGES/beyondskins.ploneday.site2009.mo
beyondskins/ploneday/site2009/locales/pt_BR/LC_MESSAGES/beyondskins.ploneday.site2009.po
beyondskins/ploneday/site2009/profiles/default/beyondskins.ploneday2009_various.txt
beyondskins/ploneday/site2009/profiles/default/cssregistry.xml
beyondskins/ploneday/site2009/profiles/default/import_steps.xml
beyondskins/ploneday/site2009/profiles/default/jsregistry.xml
beyondskins/ploneday/site2009/profiles/default/metadata.xml
beyondskins/ploneday/site2009/profiles/default/skins.xml
beyondskins/ploneday/site2009/profiles/default/viewlets.xml
beyondskins/ploneday/site2009/skins/beyondskins_ploneday_2009_images/CONTENT.txt
