Metadata-Version: 1.0
Name: beyondskins.ploneday.site2009
Version: 1.0
Summary: Installable Plone 3 theme developed to promote World Plone Day 2009 (April 22nd)
Home-page: http://www.simplesconsultoria.com.br/
Author: Simples Consultoria
Author-email: products@simplesconsultoria.com.br
License: GPL
Keywords: web zope plone theme skin simples_consultoria plone3 wpd
Platform: UNKNOWN
Classifier: Framework :: Plone
Classifier: Framework :: Zope2
Classifier: Framework :: Zope3
Classifier: Programming Language :: Python
Classifier: Topic :: Software Development :: Libraries :: Python Modules
